humane/__init__.py
humane/__main__.py
humane/cli.py
humane/emojihash.py
humane/humanid.py
humane/lists/adjectives.txt
humane/lists/adverbs.txt
humane/lists/animal-plurals.txt
humane/lists/colours.txt
humane/lists/verbs.txt
humane/tests/__init__.py
humane/tests/test_humanid.py
humane-2.0.1.dist-info/METADATA
humane-2.0.1.dist-info/WHEEL
humane-2.0.1.dist-info/entry_points.txt
humane-2.0.1.dist-info/top_level.txt
humane-2.0.1.dist-info/RECORD
