Metadata-Version: 2.1
Name: humane
Version: 2.0.1
Summary: Human Identifiers
Author-email: Daniel Hails <humane@hails.info>
Project-URL: Homepage, https://github.com/DJRHails/humane
Project-URL: Bug Tracker, https://github.com/DJRHails/humane/issues
Requires-Python: >=3.10
Requires-Dist: click
